{"ViVaStationTest":{"GetSingleStationResult":{"ID":100,"Name":"ViVateststation","Samples":[{"Name":"Byvind","Value":"V13.0","Heading":249,"Unit":"m\/s","Type":"wind","Trend":"","Msg":"","Calm":0,"Updated":"2022-02-0605:10:00","StationID":100,"Quality":"Ok","WaterLevelReference":null,"WaterLevelOffset":null},{"Name":"Medelvind","Value":"V10.8","Heading":249,"Unit":"m\/s","Type":"wind","Trend":"","Msg":"","Calm":0,"Updated":"2022-02-0605:10:00","StationID":100,"Quality":"Ok","WaterLevelReference":null,"WaterLevelOffset":null},{"Name":"Vattenstånd","Value":"30","Heading":0,"Unit":"cm","Type":"level","Trend":"","Msg":"","Calm":0,"Updated":"2022-02-0605:10:00","StationID":100,"Quality":"Ok","WaterLevelReference":"MVY","WaterLevelOffset":1.8},{"Name":"Vattentemp","Value":"4.1","Heading":0,"Unit":"°C","Type":"watertemp","Trend":"","Msg":"","Calm":0,"Updated":"2022-02-0605:10:00","StationID":100,"Quality":"Ok","WaterLevelReference":null,"WaterLevelOffset":null},{"Name":"Lufttryck","Value":"986","Heading":0,"Unit":"hPa","Type":"pressure","Trend":"","Msg":"","Calm":0,"Updated":"2022-02-0605:10:00","StationID":100,"Quality":"Ok","WaterLevelReference":null,"WaterLevelOffset":null},{"Name":"Lufttemp","Value":"4.5","Heading":0,"Unit":"°C","Type":"airtemp","Trend":"","Msg":"","Calm":0,"Updated":"2022-02-0605:10:00","StationID":100,"Quality":"Ok","WaterLevelReference":null,"WaterLevelOffset":null},{"Name":"Sikt","Value":"3000","Heading":0,"Unit":"m","Type":"sight","Trend":"","Msg":"","Calm":0,"Updated":"2022-02-0605:10:00","StationID":100,"Quality":"Ok","WaterLevelReference":null,"WaterLevelOffset":null},{"Name":"StrömYta","Value":"NO1.3","Heading":67,"Unit":"knop","Type":"stream","Trend":"","Msg":"","Calm":0,"Updated":"2022-02-0605:10:00","StationID":100,"Quality":"Ok","WaterLevelReference":null,"WaterLevelOffset":null},{"Name":"Ström3m","Value":"NO0.4","Heading":61,"Unit":"knop","Type":"stream","Trend":"","Msg":"","Calm":0,"Updated":"2022-02-0605:10:00","StationID":100,"Quality":"Ok","WaterLevelReference":null,"WaterLevelOffset":null},{"Name":"Ström7m","Value":"NO0.2","Heading":45,"Unit":"knop","Type":"stream","Trend":"","Msg":"","Calm":0,"Updated":"2022-02-0605:10:00","StationID":100,"Quality":"Ok","WaterLevelReference":null,"WaterLevelOffset":null},{"Name":"Ström15m","Value":"V0.1","Heading":278,"Unit":"knop","Type":"stream","Trend":"","Msg":"","Calm":0,"Updated":"2022-02-0605:10:00","StationID":100,"Quality":"Ok","WaterLevelReference":null,"WaterLevelOffset":null},{"Name":"Ström11m","Value":"N0.1","Heading":0,"Unit":"knop","Type":"stream","Trend":"","Msg":"","Calm":0,"Updated":"2022-02-0605:10:00","StationID":100,"Quality":"Ok","WaterLevelReference":null,"WaterLevelOffset":null}],"Felmeddelande":null}}}